ls/__init__.py
ls/sampleproject/__init__.py
ls/sampleproject/_version.py
ls/sampleproject/sator6.py
ls.sampleproject-0.4.2.data/data/my_data/data_file
ls.sampleproject-0.4.2.dist-info/DESCRIPTION.rst
ls.sampleproject-0.4.2.dist-info/LICENSE.txt
ls.sampleproject-0.4.2.dist-info/METADATA
ls.sampleproject-0.4.2.dist-info/RECORD
ls.sampleproject-0.4.2.dist-info/WHEEL
ls.sampleproject-0.4.2.dist-info/metadata.json
ls.sampleproject-0.4.2.dist-info/top_level.txt
