Metadata-Version: 2.0
Name: ls.sampleproject
Version: 0.4.2
Summary: Prints 6x6 Sator Squares
Home-page: https://github.com/linuxsoftware/ls.sampleproject
Author: David Moore
Author-email: david@linuxsoftware.co.nz
License: MIT
Keywords: sator,rotas
Platform: any
Classifier: Intended Audience :: Developers
Classifier: License :: OSI Approved :: MIT License
Classifier: Operating System :: OS Independent
Classifier: Programming Language :: Python
Classifier: Topic :: Software Development :: Libraries :: Python Modules
Requires-Dist: inflect
